syncfat/__init__.py
syncfat/__main__.py
syncfat/adapters.py
syncfat/cli.py
syncfat/sync.py
syncfat/utils/__init__.py
syncfat/utils/console.py
syncfat-0.1.0.dist-info/LICENSE
syncfat-0.1.0.dist-info/METADATA
syncfat-0.1.0.dist-info/WHEEL
syncfat-0.1.0.dist-info/entry_points.txt
syncfat-0.1.0.dist-info/top_level.txt
syncfat-0.1.0.dist-info/RECORD
