Metadata-Version: 2.1
Name: syncfat
Version: 0.1.0
Summary: Sync files to intermittent FAT mounts
Home-page: https://github.com/timheap/syncfat
Author: Tim Heap
Author-email: tim@timheap.me
License: UNKNOWN
Project-URL: Bug Tracker, https://github.com/timheap/syncfat/issues
Platform: UNKNOWN
Classifier: Programming Language :: Python :: 3
Classifier: License :: OSI Approved :: MIT License
Classifier: Operating System :: OS Independent
Requires-Python: >=3.9
Requires-Dist: tqdm (~=4.60.0)
